<xml xmlns:v="urn:schemas-microsoft-com:vml"
 xmlns:o="urn:schemas-microsoft-com:office:office"
 xmlns:p="urn:schemas-microsoft-com:office:powerpoint"
 xmlns:oa="urn:schemas-microsoft-com:office:activation">
 <o:shapelayout v:ext="edit">
  <o:idmap v:ext="edit" data="84"/>
 </o:shapelayout><p:shaperange id="_x0000_s86018">
  <v:shape id="_x0000_s86018" type="#_x0000_m4098" style='position:absolute;
   left:36.375pt;top:0;width:647.25pt;height:111.625pt'>
   <v:fill o:detectmouseclick="f"/>
   <v:stroke o:forcedash="f"/>
   <o:lock v:ext="edit" text="f"/>
   <p:placeholder type="title"/>
  </v:shape><v:shape id="_x0000_s86090" type="#_x0000_m4099" style='position:absolute;
   left:36pt;top:400pt;width:9in;height:114.875pt' o:spt="1" path="m,l,21600r21600,l21600,xe"
   filled="f" fillcolor="#bbe0e3 [4]" stroked="f" strokecolor="black [1]">
   <v:fill color2="white [0]" o:detectmouseclick="f"/>
   <v:stroke joinstyle="miter" o:forcedash="f"/>
   <v:shadow color="gray [2]"/>
   <v:path gradientshapeok="t" o:connecttype="rect"/>
   <o:lock v:ext="edit" text="f" grouping="t"/>
   <p:placeholder type="body" position="1"/>
  </v:shape><v:group id="_x0000_s86103" style='position:absolute;left:11.25pt;
   top:137.5pt;width:698.625pt;height:241.375pt' coordorigin="90,1003"
   coordsize="5589,1931" o:tableproperties="1" o:tablelimits="31.25pt 30.25pt 24.25pt 48.125pt 46.125pt 47.125pt">
   <o:lock v:ext="edit" rotation="t"/>
   <v:rect id="_x0000_s86104" style='position:absolute;left:3253;top:1003;
    width:2426;height:250' filled="f" fillcolor="#e1e8f3" stroked="f"
    strokecolor="black [1]">
    <v:fill alignshape="f" o:detectmouseclick="t"/>
    <v:shadow color="gray [2]"/>
   </v:rect><v:rect id="_x0000_s86105" style='position:absolute;left:3138;
    top:1003;width:115;height:250' filled="f" fillcolor="#e1e8f3" stroked="f"
    strokecolor="black [1]">
    <v:fill alignshape="f" o:detectmouseclick="t"/>
    <v:shadow color="gray [2]"/>
   </v:rect><v:rect id="_x0000_s86106" style='position:absolute;left:1251;
    top:1003;width:1887;height:250' filled="f" fillcolor="#bbe0e3 [4]"
    stroked="f" strokecolor="black [1]">
    <v:fill color2="white [0]" alignshape="f" o:detectmouseclick="t"/>
    <v:shadow color="gray [2]"/>
   </v:rect><v:rect id="_x0000_s86107" style='position:absolute;left:90;top:1003;
    width:1161;height:492' filled="f" fillcolor="#bbe0e3 [4]" stroked="f"
    strokecolor="black [1]">
    <v:fill color2="white [0]" alignshape="f" o:detectmouseclick="t"/>
    <v:shadow color="gray [2]"/>
   </v:rect><v:rect id="_x0000_s86108" style='position:absolute;left:3138;
    top:2531;width:115;height:403' filled="f" fillcolor="#e1e8f3" stroked="f"
    strokecolor="black [1]">
    <v:fill alignshape="f" o:detectmouseclick="t"/>
    <v:shadow color="gray [2]"/>
   </v:rect><v:rect id="_x0000_s86109" style='position:absolute;left:3138;
    top:2128;width:115;height:403' filled="f" fillcolor="#e1e8f3" stroked="f"
    strokecolor="black [1]">
    <v:fill alignshape="f" o:detectmouseclick="t"/>
    <v:shadow color="gray [2]"/>
   </v:rect><v:rect id="_x0000_s86110" style='position:absolute;left:3138;
    top:1725;width:115;height:403' filled="f" fillcolor="#e1e8f3" stroked="f"
    strokecolor="black [1]">
    <v:fill alignshape="f" o:detectmouseclick="t"/>
    <v:shadow color="gray [2]"/>
   </v:rect><v:rect id="_x0000_s86111" style='position:absolute;left:3138;
    top:1495;width:115;height:230' filled="f" fillcolor="#e1e8f3" stroked="f"
    strokecolor="black [1]">
    <v:fill alignshape="f" o:detectmouseclick="t"/>
    <v:shadow color="gray [2]"/>
   </v:rect><v:rect id="_x0000_s86112" style='position:absolute;left:3138;
    top:1253;width:115;height:242' filled="f" fillcolor="#e1e8f3" stroked="f"
    strokecolor="black [1]">
    <v:fill alignshape="f" o:detectmouseclick="t"/>
    <v:shadow color="gray [2]"/>
   </v:rect><v:rect id="_x0000_s86113" style='position:absolute;left:2679;
    top:2531;width:459;height:403' filled="f" fillcolor="#bbe0e3 [4]"
    stroked="f" strokecolor="black [1]">
    <v:fill color2="white [0]" alignshape="f" o:detectmouseclick="t"/>
    <v:shadow color="gray [2]"/>
   </v:rect><v:rect id="_x0000_s86114" style='position:absolute;left:2679;
    top:2128;width:459;height:403' filled="f" fillcolor="#bbe0e3 [4]"
    stroked="f" strokecolor="black [1]">
    <v:fill color2="white [0]" alignshape="f" o:detectmouseclick="t"/>
    <v:shadow color="gray [2]"/>
   </v:rect><v:rect id="_x0000_s86115" style='position:absolute;left:2679;
    top:1725;width:459;height:403' filled="f" fillcolor="#bbe0e3 [4]"
    stroked="f" strokecolor="black [1]">
    <v:fill color2="white [0]" alignshape="f" o:detectmouseclick="t"/>
    <v:shadow color="gray [2]"/>
   </v:rect><v:rect id="_x0000_s86116" style='position:absolute;left:2679;
    top:1495;width:459;height:230' filled="f" fillcolor="#bbe0e3 [4]"
    stroked="f" strokecolor="black [1]">
    <v:fill color2="white [0]" alignshape="f" o:detectmouseclick="t"/>
    <v:shadow color="gray [2]"/>
   </v:rect><v:rect id="_x0000_s86117" style='position:absolute;left:2195;
    top:2531;width:484;height:403' filled="f" fillcolor="#bbe0e3 [4]"
    stroked="f" strokecolor="black [1]">
    <v:fill color2="white [0]" alignshape="f" o:detectmouseclick="t"/>
    <v:shadow color="gray [2]"/>
   </v:rect><v:rect id="_x0000_s86118" style='position:absolute;left:2195;
    top:2128;width:484;height:403' filled="f" fillcolor="#bbe0e3 [4]"
    stroked="f" strokecolor="black [1]">
    <v:fill color2="white [0]" alignshape="f" o:detectmouseclick="t"/>
    <v:shadow color="gray [2]"/>
   </v:rect><v:rect id="_x0000_s86119" style='position:absolute;left:2195;
    top:1725;width:484;height:403' filled="f" fillcolor="#bbe0e3 [4]"
    stroked="f" strokecolor="black [1]">
    <v:fill color2="white [0]" alignshape="f" o:detectmouseclick="t"/>
    <v:shadow color="gray [2]"/>
   </v:rect><v:rect id="_x0000_s86120" style='position:absolute;left:2195;
    top:1495;width:484;height:230' filled="f" fillcolor="#bbe0e3 [4]"
    stroked="f" strokecolor="black [1]">
    <v:fill color2="white [0]" alignshape="f" o:detectmouseclick="t"/>
    <v:shadow color="gray [2]"/>
   </v:rect><v:rect id="_x0000_s86121" style='position:absolute;left:2195;
    top:1253;width:943;height:242' filled="f" fillcolor="#bbe0e3 [4]"
    stroked="f" strokecolor="black [1]">
    <v:fill color2="white [0]" alignshape="f" o:detectmouseclick="t"/>
    <v:shadow color="gray [2]"/>
   </v:rect><v:rect id="_x0000_s86122" style='position:absolute;left:1711;
    top:2531;width:484;height:403' filled="f" fillcolor="#bbe0e3 [4]"
    stroked="f" strokecolor="black [1]">
    <v:fill color2="white [0]" alignshape="f" o:detectmouseclick="t"/>
    <v:shadow color="gray [2]"/>
   </v:rect><v:rect id="_x0000_s86123" style='position:absolute;left:1711;
    top:2128;width:484;height:403' filled="f" fillcolor="#bbe0e3 [4]"
    stroked="f" strokecolor="black [1]">
    <v:fill color2="white [0]" alignshape="f" o:detectmouseclick="t"/>
    <v:shadow color="gray [2]"/>
   </v:rect><v:rect id="_x0000_s86124" style='position:absolute;left:1711;
    top:1725;width:484;height:403' filled="f" fillcolor="#bbe0e3 [4]"
    stroked="f" strokecolor="black [1]">
    <v:fill color2="white [0]" alignshape="f" o:detectmouseclick="t"/>
    <v:shadow color="gray [2]"/>
   </v:rect><v:rect id="_x0000_s86125" style='position:absolute;left:1711;
    top:1495;width:484;height:230' filled="f" fillcolor="#bbe0e3 [4]"
    stroked="f" strokecolor="black [1]">
    <v:fill color2="white [0]" alignshape="f" o:detectmouseclick="t"/>
    <v:shadow color="gray [2]"/>
   </v:rect><v:rect id="_x0000_s86126" style='position:absolute;left:4469;
    top:1253;width:1210;height:242' filled="f" fillcolor="#bbe0e3 [4]"
    stroked="f" strokecolor="black [1]">
    <v:fill color2="white [0]" alignshape="f" o:detectmouseclick="t"/>
    <v:shadow color="gray [2]"/>
   </v:rect><v:rect id="_x0000_s86127" style='position:absolute;left:3253;
    top:1253;width:1216;height:242' filled="f" fillcolor="#bbe0e3 [4]"
    stroked="f" strokecolor="black [1]">
    <v:fill color2="white [0]" alignshape="f" o:detectmouseclick="t"/>
    <v:shadow color="gray [2]"/>
   </v:rect><v:rect id="_x0000_s86128" style='position:absolute;left:1251;
    top:1253;width:944;height:242' filled="f" fillcolor="#bbe0e3 [4]"
    stroked="f" strokecolor="black [1]">
    <v:fill color2="white [0]" alignshape="f" o:detectmouseclick="t"/>
    <v:shadow color="gray [2]"/>
   </v:rect><v:rect id="_x0000_s86129" style='position:absolute;left:5074;
    top:1495;width:605;height:230' filled="f" fillcolor="#bbe0e3 [4]"
    stroked="f" strokecolor="black [1]">
    <v:fill color2="white [0]" alignshape="f" o:detectmouseclick="t"/>
    <v:shadow color="gray [2]"/>
   </v:rect><v:rect id="_x0000_s86130" style='position:absolute;left:4469;
    top:1495;width:605;height:230' filled="f" fillcolor="#bbe0e3 [4]"
    stroked="f" strokecolor="black [1]">
    <v:fill color2="white [0]" alignshape="f" o:detectmouseclick="t"/>
    <v:shadow color="gray [2]"/>
   </v:rect><v:rect id="_x0000_s86131" style='position:absolute;left:3864;
    top:1495;width:605;height:230' filled="f" fillcolor="#bbe0e3 [4]"
    stroked="f" strokecolor="black [1]">
    <v:fill color2="white [0]" alignshape="f" o:detectmouseclick="t"/>
    <v:shadow color="gray [2]"/>
   </v:rect><v:rect id="_x0000_s86132" style='position:absolute;left:3253;
    top:1495;width:611;height:230' filled="f" fillcolor="#bbe0e3 [4]"
    stroked="f" strokecolor="black [1]">
    <v:fill color2="white [0]" alignshape="f" o:detectmouseclick="t"/>
    <v:shadow color="gray [2]"/>
   </v:rect><v:rect id="_x0000_s86133" style='position:absolute;left:1251;
    top:1495;width:460;height:230' filled="f" fillcolor="#bbe0e3 [4]"
    stroked="f" strokecolor="black [1]">
    <v:fill color2="white [0]" alignshape="f" o:detectmouseclick="t"/>
    <v:shadow color="gray [2]"/>
   </v:rect><v:rect id="_x0000_s86134" style='position:absolute;left:90;top:1495;
    width:1161;height:230' filled="f" fillcolor="#bbe0e3 [4]" stroked="f"
    strokecolor="black [1]">
    <v:fill color2="white [0]" alignshape="f" o:detectmouseclick="t"/>
    <v:shadow color="gray [2]"/>
   </v:rect><v:rect id="_x0000_s86135" style='position:absolute;left:5074;
    top:2531;width:605;height:403' filled="f" fillcolor="#e1e8f3" stroked="f"
    strokecolor="black [1]">
    <v:fill alignshape="f" o:detectmouseclick="t"/>
    <v:shadow color="gray [2]"/>
   </v:rect><v:rect id="_x0000_s86136" style='position:absolute;left:4469;
    top:2531;width:605;height:403' filled="f" fillcolor="#e1e8f3" stroked="f"
    strokecolor="black [1]">
    <v:fill alignshape="f" o:detectmouseclick="t"/>
    <v:shadow color="gray [2]"/>
   </v:rect><v:rect id="_x0000_s86137" style='position:absolute;left:3864;
    top:2531;width:605;height:403' filled="f" fillcolor="#e1e8f3" stroked="f"
    strokecolor="black [1]">
    <v:fill alignshape="f" o:detectmouseclick="t"/>
    <v:shadow color="gray [2]"/>
   </v:rect><v:rect id="_x0000_s86138" style='position:absolute;left:3253;
    top:2531;width:611;height:403' filled="f" fillcolor="#e1e8f3" stroked="f"
    strokecolor="black [1]">
    <v:fill alignshape="f" o:detectmouseclick="t"/>
    <v:shadow color="gray [2]"/>
   </v:rect><v:rect id="_x0000_s86139" style='position:absolute;left:1251;
    top:2531;width:460;height:403' filled="f" fillcolor="#bbe0e3 [4]"
    stroked="f" strokecolor="black [1]">
    <v:fill color2="white [0]" alignshape="f" o:detectmouseclick="t"/>
    <v:shadow color="gray [2]"/>
   </v:rect><v:rect id="_x0000_s86140" style='position:absolute;left:90;top:2531;
    width:1161;height:403' filled="f" fillcolor="#bbe0e3 [4]" stroked="f"
    strokecolor="black [1]">
    <v:fill color2="white [0]" alignshape="f" o:detectmouseclick="t"/>
    <v:shadow color="gray [2]"/>
   </v:rect><v:rect id="_x0000_s86141" style='position:absolute;left:5074;
    top:2128;width:605;height:403' filled="f" fillcolor="#e1e8f3" stroked="f"
    strokecolor="black [1]">
    <v:fill alignshape="f" o:detectmouseclick="t"/>
    <v:shadow color="gray [2]"/>
   </v:rect><v:rect id="_x0000_s86142" style='position:absolute;left:4469;
    top:2128;width:605;height:403' filled="f" fillcolor="#e1e8f3" stroked="f"
    strokecolor="black [1]">
    <v:fill alignshape="f" o:detectmouseclick="t"/>
    <v:shadow color="gray [2]"/>
   </v:rect><v:rect id="_x0000_s86143" style='position:absolute;left:3864;
    top:2128;width:605;height:403' filled="f" fillcolor="#e1e8f3" stroked="f"
    strokecolor="black [1]">
    <v:fill alignshape="f" o:detectmouseclick="t"/>
    <v:shadow color="gray [2]"/>
   </v:rect><v:rect id="_x0000_s86144" style='position:absolute;left:3253;
    top:2128;width:611;height:403' filled="f" fillcolor="#e1e8f3" stroked="f"
    strokecolor="black [1]">
    <v:fill alignshape="f" o:detectmouseclick="t"/>
    <v:shadow color="gray [2]"/>
   </v:rect><v:rect id="_x0000_s86145" style='position:absolute;left:1251;
    top:2128;width:460;height:403' filled="f" fillcolor="#bbe0e3 [4]"
    stroked="f" strokecolor="black [1]">
    <v:fill color2="white [0]" alignshape="f" o:detectmouseclick="t"/>
    <v:shadow color="gray [2]"/>
   </v:rect><v:rect id="_x0000_s86146" style='position:absolute;left:90;top:2128;
    width:1161;height:403' filled="f" fillcolor="#bbe0e3 [4]" stroked="f"
    strokecolor="black [1]">
    <v:fill color2="white [0]" alignshape="f" o:detectmouseclick="t"/>
    <v:shadow color="gray [2]"/>
   </v:rect><v:rect id="_x0000_s86147" style='position:absolute;left:5074;
    top:1725;width:605;height:403' filled="f" fillcolor="#e1e8f3" stroked="f"
    strokecolor="black [1]">
    <v:fill alignshape="f" o:detectmouseclick="t"/>
    <v:shadow color="gray [2]"/>
   </v:rect><v:rect id="_x0000_s86148" style='position:absolute;left:4469;
    top:1725;width:605;height:403' filled="f" fillcolor="#e1e8f3" stroked="f"
    strokecolor="black [1]">
    <v:fill alignshape="f" o:detectmouseclick="t"/>
    <v:shadow color="gray [2]"/>
   </v:rect><v:rect id="_x0000_s86149" style='position:absolute;left:3864;
    top:1725;width:605;height:403' filled="f" fillcolor="#e1e8f3" stroked="f"
    strokecolor="black [1]">
    <v:fill alignshape="f" o:detectmouseclick="t"/>
    <v:shadow color="gray [2]"/>
   </v:rect><v:rect id="_x0000_s86150" style='position:absolute;left:3253;
    top:1725;width:611;height:403' filled="f" fillcolor="#e1e8f3" stroked="f"
    strokecolor="black [1]">
    <v:fill alignshape="f" o:detectmouseclick="t"/>
    <v:shadow color="gray [2]"/>
   </v:rect><v:rect id="_x0000_s86151" style='position:absolute;left:1251;
    top:1725;width:460;height:403' filled="f" fillcolor="#bbe0e3 [4]"
    stroked="f" strokecolor="black [1]">
    <v:fill color2="white [0]" alignshape="f" o:detectmouseclick="t"/>
    <v:shadow color="gray [2]"/>
   </v:rect><v:rect id="_x0000_s86152" style='position:absolute;left:90;top:1725;
    width:1161;height:403' filled="f" fillcolor="#bbe0e3 [4]" stroked="f"
    strokecolor="black [1]">
    <v:fill color2="white [0]" alignshape="f" o:detectmouseclick="t"/>
    <v:shadow color="gray [2]"/>
   </v:rect><v:line id="_x0000_s86153" style='position:absolute' from="90,1003"
    to="5679,1003" strokecolor="black [1]" strokeweight="2.25pt">
    <v:stroke endcap="square" imagealignshape="f"/>
    <v:shadow color="gray [2]"/>
   </v:line><v:line id="_x0000_s86154" style='position:absolute' from="90,2128"
    to="5679,2128" strokecolor="black [1]" strokeweight="1pt">
    <v:stroke imagealignshape="f"/>
    <v:shadow color="gray [2]"/>
   </v:line><v:line id="_x0000_s86155" style='position:absolute' from="90,2531"
    to="5679,2531" strokecolor="black [1]" strokeweight="1pt">
    <v:stroke imagealignshape="f"/>
    <v:shadow color="gray [2]"/>
   </v:line><v:line id="_x0000_s86156" style='position:absolute' from="90,2934"
    to="5679,2934" strokecolor="black [1]" strokeweight="2.25pt">
    <v:stroke endcap="square" imagealignshape="f"/>
    <v:shadow color="gray [2]"/>
   </v:line><v:line id="_x0000_s86157" style='position:absolute' from="90,1003"
    to="90,2934" strokecolor="black [1]" strokeweight="2.25pt">
    <v:stroke endcap="square" imagealignshape="f"/>
    <v:shadow color="gray [2]"/>
   </v:line><v:line id="_x0000_s86158" style='position:absolute' from="1251,1003"
    to="1251,2934" strokecolor="black [1]" strokeweight="1pt">
    <v:stroke imagealignshape="f"/>
    <v:shadow color="gray [2]"/>
   </v:line><v:line id="_x0000_s86159" style='position:absolute' from="5679,1003"
    to="5679,2934" strokecolor="black [1]" strokeweight="2.25pt">
    <v:stroke endcap="square" imagealignshape="f"/>
    <v:shadow color="gray [2]"/>
   </v:line><v:line id="_x0000_s86160" style='position:absolute' from="90,1725"
    to="5679,1725" strokecolor="black [1]" strokeweight="1pt">
    <v:stroke imagealignshape="f"/>
    <v:shadow color="gray [2]"/>
   </v:line><v:line id="_x0000_s86161" style='position:absolute' from="90,1495"
    to="5679,1495" strokecolor="black [1]" strokeweight="1pt">
    <v:stroke imagealignshape="f"/>
    <v:shadow color="gray [2]"/>
   </v:line><v:line id="_x0000_s86162" style='position:absolute' from="3138,1003"
    to="3138,2934" strokecolor="black [1]" strokeweight="1pt">
    <v:stroke imagealignshape="f"/>
    <v:shadow color="gray [2]"/>
   </v:line><v:line id="_x0000_s86163" style='position:absolute' from="3253,1003"
    to="3253,2934" strokecolor="black [1]" strokeweight="1pt">
    <v:stroke imagealignshape="f"/>
    <v:shadow color="gray [2]"/>
   </v:line><v:line id="_x0000_s86164" style='position:absolute' from="2195,1253"
    to="2195,2934" strokecolor="black [1]" strokeweight="1pt">
    <v:stroke imagealignshape="f"/>
    <v:shadow color="gray [2]"/>
   </v:line><v:line id="_x0000_s86165" style='position:absolute' from="4469,1253"
    to="4469,2934" strokecolor="black [1]" strokeweight="1pt">
    <v:stroke imagealignshape="f"/>
    <v:shadow color="gray [2]"/>
   </v:line><v:line id="_x0000_s86166" style='position:absolute' from="1711,1495"
    to="1711,2934" strokecolor="black [1]" strokeweight="1pt">
    <v:stroke imagealignshape="f"/>
    <v:shadow color="gray [2]"/>
   </v:line><v:line id="_x0000_s86167" style='position:absolute' from="2679,1495"
    to="2679,2934" strokecolor="black [1]" strokeweight="1pt">
    <v:stroke imagealignshape="f"/>
    <v:shadow color="gray [2]"/>
   </v:line><v:line id="_x0000_s86168" style='position:absolute' from="3864,1495"
    to="3864,2934" strokecolor="black [1]" strokeweight="1pt">
    <v:stroke imagealignshape="f"/>
    <v:shadow color="gray [2]"/>
   </v:line><v:line id="_x0000_s86169" style='position:absolute' from="5074,1495"
    to="5074,2934" strokecolor="black [1]" strokeweight="1pt">
    <v:stroke imagealignshape="f"/>
    <v:shadow color="gray [2]"/>
   </v:line><v:line id="_x0000_s86170" style='position:absolute' from="1251,1253"
    to="5679,1253" strokecolor="black [1]" strokeweight="1pt">
    <v:stroke imagealignshape="f"/>
    <v:shadow color="gray [2]"/>
   </v:line></v:group></p:shaperange>
</xml>