<xml xmlns:v="urn:schemas-microsoft-com:vml"
 xmlns:o="urn:schemas-microsoft-com:office:office"
 xmlns:p="urn:schemas-microsoft-com:office:powerpoint"
 xmlns:oa="urn:schemas-microsoft-com:office:activation">
 <p:presentation sizeof="screen" notessizex="4408" notessizey="5848"
  gridspacingx="46448" gridspacingy="46448" hasautolinks="t">
  <p:master id="4" slidesn="1C00DA4,E0F4EF80" type="main" href="master04.htm"
   xmlhref="master04.xml" template="Radial" layout="title_body"
   slots="title,body,dateTime,footer,slideNumber">
   <p:schemes>
    <p:colorscheme
     colors="#FFFFFF,#000000,#669999,#FFFFFF,#99CCFF,#9999FF,#996666,#6666CC"/>
    <p:colorscheme
     colors="#FFFFFF,#000000,#817F3F,#FFFFFF,#FFCC00,#CC9900,#996666,#C94503"/>
    <p:colorscheme
     colors="#800000,#FFFFFF,#CC6600,#FFFFFF,#FF6600,#33CCCC,#99FF33,#CC3300"/>
    <p:colorscheme
     colors="#431A01,#FFFFFF,#993300,#FFFFFF,#FFCC00,#FF9966,#FF6600,#CC3300"/>
    <p:colorscheme
     colors="#260000,#FFFFFF,#75878B,#FFFFFF,#0099CC,#FF3300,#FFCC00,#CC0000"/>
    <p:colorscheme
     colors="#000000,#FFFFFF,#666699,#FFFFFF,#9966FF,#99CCFF,#FFFFCC,#6600CC"/>
    <p:colorscheme
     colors="#2A2A40,#FFFFFF,#666699,#FFFFFF,#006699,#CC9900,#CC6600,#6C948A"/>
    <p:colorscheme
     colors="#2B335B,#FFFFFF,#BECBD8,#FFFFFF,#0099CC,#B5DBE3,#FFCC00,#58648C"/>
    <p:colorscheme
     colors="#000099,#FFFFFF,#3333FF,#FFFFFF,#339966,#9999FF,#FFFF99,#17A0D1"/>
    <p:colorscheme
     colors="#354418,#FFFFFF,#808000,#FFFFFF,#60897C,#99CC00,#CCCC00,#669900"/>
   </p:schemes>
  </p:master>
  <p:master id="5" slidesn="1C00DA4,E0F4EF80" type="title" href="master05.htm"
   xmlhref="master05.xml" layout="title_subtitle"
   slots="centerTitle,subTitle,dateTime,footer,slideNumber"/>
  <p:master id="1" slidesn="1C44421,7FD65920" type="notes" href="master01.htm"
   layout="notes" slots="header,dateTime,slideImage,body,footer,slideNumber"/>
  <p:slide id="1" slidesn="1C4428A,F067C8B0" href="slide0001.htm"
   masterhref="master05.htm" layout="title_subtitle"
   slots="centerTitle,subTitle"/>
  <p:slide id="32" slidesn="1C4480C,15B753C0" href="slide0032.htm"
   layout="title_body" slots="title,body"/>
  <p:slide id="17" slidesn="1C4477A,6754F620" href="slide0017.htm"
   layout="title_body" slots="title,body"/>
  <p:slide id="33" slidesn="1C40B7A,4E80B530" href="slide0033.htm"
   layout="title_body" slots="title,object"/>
  <p:slide id="34" slidesn="1C40C94,5B189F90" href="slide0034.htm"
   layout="title_body" slots="title,object"/>
  <p:slide id="3" slidesn="1C4428B,3580D720" href="slide0003.htm"
   layout="title_body" slots="title,body"/>
  <p:slide id="31" slidesn="1C40B7A,461DA4C0" href="slide0031.htm"
   layout="2_columns" slots="title,body,object"/>
  <p:slide id="21" slidesn="1C4428B,3580D720" href="slide0021.htm"
   layout="title_body" slots="title,body"/>
  <p:slide id="35" slidesn="1C442A8,11DF91E0" href="slide0035.htm"
   layout="2_columns" slots="title,object,object"/>
  <p:slide id="24" slidesn="1C4311D,BDC7B150" href="slide0024.htm"
   layout="title_body" slots="title,body"/>
  <p:slide id="25" slidesn="1C42D6B,BA314C00" href="slide0025.htm"
   layout="title_body" slots="title,object"/>
  <p:slide id="27" slidesn="1C42E3B,66B802A0" href="slide0027.htm"
   layout="title_body" slots="title,object"/>
  <p:slide id="29" slidesn="1C4477D,432DDDE0" href="slide0029.htm"
   layout="title_body" slots="title,body"/>
  <p:slide id="30" slidesn="1C4477F,C73A1E30" href="slide0030.htm"
   layout="2_columns" slots="title,body,object"/>
  <p:slide id="8" slidesn="1C442AB,5A42E1F0" href="slide0008.htm"
   layout="2_columns" slots="title,body,object"/>
  <p:viewstate type="slideView" restoredleft="163" restoredtop="860"
   manualadjustleft="t" manualadjusttop="t" hideoutlineicons="t"/>
  <p:font name="Arial" charset="0" type="4"/>
  <p:font name="Times New Roman" charset="0" type="6" family="18"/>
  <p:font name="Wingdings" charset="2" type="6" family="2"/>
  <p:font name="新細明體" charset="136" type="4"/>
  <p:font name="Arial Black" charset="0" type="6" family="34"/>
  <p:headersfooters slidenumber="t" formatid="0" nouserdate="t" noheader="t"
   todaydate="t"/>
  <p:headersfooters notes="t" slidenumber="t"/>
  <p:pptdocumentsettings framecolors="WhiteTextOnBlack" hideslideanimation="t"
   browsersupport="v4"/>
  <p:htmlpublishsettings browsersupport="v4"
   href="C:\Documents and Settings\khoeper\My Documents\Homepage_comsec\seminarfiles\christina.htm"
   hidespeakernote="t"/>
 </p:presentation>
 <o:shapedefaults v:ext="edit" spidmax="114697"/>
</xml>